body/__init__.py
body/__main__.py
body/constants.py
body/errors.py
body/external.py
body/regex.py
body/response.py
body/rest.py
body/service.py
body_oc-2.2.0.dist-info/METADATA
body_oc-2.2.0.dist-info/WHEEL
body_oc-2.2.0.dist-info/licenses/LICENSE
body_oc-2.2.0.dist-info/RECORD
