Metadata-Version: 2.4
Name: body_oc
Version: 2.2.0
Summary: Body contains shared concepts among all body parts
Project-URL: Source, https://github.com/ouroboroscoding/body
Project-URL: Tracker, https://github.com/ouroboroscoding/body/issues
Author-email: "Chris Nasr - Ouroboros Coding Inc." <chris@ouroboroscoding.com>
Maintainer-email: "Chris Nasr - Ouroboros Coding Inc." <chris@ouroboroscoding.com>
License-File: LICENSE
Requires-Python: >=3.10
Requires-Dist: bottle<0.14,>=0.13.2
Requires-Dist: gunicorn<23.1,>=23.0.0
Requires-Dist: jobject<1.1.0,>=1.0.3
Requires-Dist: jsonb<1.1.0,>=1.0.0
Requires-Dist: memory-oc<1.1,>=1.0.1
Requires-Dist: requests<2.33,>=2.32.3
Requires-Dist: strings-oc<1.1,>=1.0.7
Requires-Dist: tools-oc<1.3,>=1.2.5
Requires-Dist: undefined-oc<1.1,>=1.0.0
